{
    "general": {
        "test_name": "main",
        "datalake_location": "mongodb",
        "dataset": "wikiturlsnap",
        "size": "standard",
        "mapping_id_file": "",
        "numeric_columns_file": "",
        "blacklist": [],
        "k": 20,
        "num_query_samples": 50000,
        "num_cpu": 72,
        
        "josie_db_connection_info": {
            "drivername":   "postgresql",
            "database":     "JOSIEDB",
            "username":     "nanni",
            "password":     "",
            "port":         5442,
            "host":         "127.0.0.1"
        }
    },
    
    "data_preparation": {
        "algorithms": [
            "josie", "lshforest", "embedding"
        ],
        "modes": [
            "set", "bag", "ft"
        ],
        "spark_config": {
            "spark.app.name":               "JOSIE Data Preparation",
            "spark.master":                 "local[64]",
            "spark.executor.memory":        "100g",
            "spark.driver.memory":          "20g",
            "spark.local.dir":              "/path/to/tmp/spark",
            "spark.driver.maxResultSize":   "12g",
            "spark.jars.packages":          "org.mongodb.spark:mongo-spark-connector_2.12:10.3.0",
            "spark.driver.extraClassPath":  "/path/to/driver/jar"
        },
        "token_table_on_mem": false,
        "num_perm": 256,
        "l": 32,
        "exec_now": false
    },

    "sample_queries": {
        "exec_now": false
    },

    "query": {
        "algorithms": [
            "josie"
        ],
        "modes": [
            "set"
        ],
        "exec_now": false
    },

    "extract": {
        "clear_results_table": false,
        "exec_now": true
    },

    "analyses": {
        "p_values": [
            1, 5, 10, 20
        ],
        "exec_now": false
    },

    "clean": {
        "algorithms": [
            "josie", "lshforest", "embedding"
        ],
        "modes": [
            "set", "bag", "ft", "cft"
        ],
        "exec_now": false
    }
}